{"commitInfo":{"timestamp":1783010711207,"operation":"WRITE","operationParameters":{"mode":"Overwrite","partitionBy":"[]"},"isolationLevel":"Serializable","isBlindAppend":false,"operationMetrics":{"numFiles":"1","numOutputRows":"6","numOutputBytes":"1200"},"engineInfo":"Apache-Spark/3.5.1 Delta-Lake/3.2.0","txnId":"88032783-92e8-4ac7-a03a-92c850c0df15"}}
{"metaData":{"id":"fef92f06-9472-4907-a1e6-020146d60e4b","format":{"provider":"parquet","options":{}},"schemaString":"{\"type\":\"struct\",\"fields\":[{\"name\":\"status\",\"type\":\"string\",\"nullable\":true,\"metadata\":{}},{\"name\":\"total_events\",\"type\":\"long\",\"nullable\":true,\"metadata\":{}},{\"name\":\"total_shipments\",\"type\":\"long\",\"nullable\":true,\"metadata\":{}}]}","partitionColumns":[],"configuration":{},"createdTime":1783010703556}}
{"protocol":{"minReaderVersion":1,"minWriterVersion":2}}
{"add":{"path":"part-00000-497c2e49-4356-4091-88e0-f1f80fefd36f-c000.snappy.parquet","partitionValues":{},"size":1200,"modificationTime":1783010710427,"dataChange":true,"stats":"{\"numRecords\":6,\"minValues\":{\"status\":\"ARRIVED_AT_HUB\",\"total_events\":33,\"total_shipments\":33},\"maxValues\":{\"status\":\"PICKED_UP\",\"total_events\":285,\"total_shipments\":285},\"nullCount\":{\"status\":0,\"total_events\":0,\"total_shipments\":0}}"}}
